{
  "slug": "saint-constant",
  "pdf": "/tmp/stconstant.pdf",
  "page": 1,
  "pageW": 2384,
  "pageH": 3370,
  "gcps": [
    {
      "fx": 0.5318365929026847,
      "fy": 0.16875347737091992,
      "lon": -73.60409349173105,
      "lat": 45.37706670721144,
      "source": "cadastre-parcel-corner-match",
      "independent": true,
      "note": "autonomous cadastre parcel/linework corner match #1; seed_nearest=0.02m; fit_residual=1.18m"
    },
    {
      "fx": 0.6998315593456376,
      "fy": 0.16271791542433234,
      "lon": -73.58379080813184,
      "lat": 45.37805801394217,
      "source": "cadastre-parcel-corner-match",
      "independent": true,
      "note": "autonomous cadastre parcel/linework corner match #2; seed_nearest=0.06m; fit_residual=0.97m"
    },
    {
      "fx": 0.7421891385318792,
      "fy": 0.24625486832640947,
      "lon": -73.57867186179153,
      "lat": 45.36434032896639,
      "source": "cadastre-parcel-corner-match",
      "independent": true,
      "note": "autonomous cadastre parcel/linework corner match #3; seed_nearest=0.09m; fit_residual=0.21m"
    },
    {
      "fx": 0.4687926017281878,
      "fy": 0.16314563242136496,
      "lon": -73.61171378440353,
      "lat": 45.377987078170754,
      "source": "cadastre-parcel-corner-match",
      "independent": true,
      "note": "autonomous cadastre parcel/linework corner match #4; seed_nearest=0.09m; fit_residual=1.23m"
    },
    {
      "fx": 0.7985151662080537,
      "fy": 0.17461169325816028,
      "lon": -73.5718642174644,
      "lat": 45.37610377087475,
      "source": "cadastre-parcel-corner-match",
      "independent": true,
      "note": "autonomous cadastre parcel/linework corner match #5; seed_nearest=0.09m; fit_residual=0.74m"
    },
    {
      "fx": 0.9743128014932886,
      "fy": 0.28846902819584574,
      "lon": -73.55061785096427,
      "lat": 45.35740831050097,
      "source": "cadastre-parcel-corner-match",
      "independent": true,
      "note": "autonomous cadastre parcel/linework corner match #6; seed_nearest=0.15m; fit_residual=0.65m"
    },
    {
      "fx": 0.9057305867281878,
      "fy": 0.21135942135905045,
      "lon": -73.5589083784669,
      "lat": 45.370071341432805,
      "source": "cadastre-parcel-corner-match",
      "independent": true,
      "note": "autonomous cadastre parcel/linework corner match #7; seed_nearest=0.15m; fit_residual=0.14m"
    },
    {
      "fx": 0.4327269688506712,
      "fy": 0.27760803041543025,
      "lon": -73.61607028474813,
      "lat": 45.35919412953654,
      "source": "cadastre-parcel-corner-match",
      "independent": true,
      "note": "autonomous cadastre parcel/linework corner match #8; seed_nearest=0.15m; fit_residual=0.47m"
    },
    {
      "fx": 0.36658616035234887,
      "fy": 0.3821181843442137,
      "lon": -73.62406644421361,
      "lat": 45.34203390500628,
      "source": "cadastre-parcel-corner-match",
      "independent": true,
      "note": "autonomous cadastre parcel/linework corner match #9; seed_nearest=0.18m; fit_residual=0.64m"
    },
    {
      "fx": 0.6675165163506711,
      "fy": 0.3890091802670623,
      "lon": -73.5876958143163,
      "lat": 45.340899486581996,
      "source": "cadastre-parcel-corner-match",
      "independent": true,
      "note": "autonomous cadastre parcel/linework corner match #10; seed_nearest=0.20m; fit_residual=1.06m"
    },
    {
      "fx": 0.9407131527852349,
      "fy": 0.11185204934124626,
      "lon": -73.55467644031624,
      "lat": 45.386408802854156,
      "source": "cadastre-parcel-corner-match",
      "independent": true,
      "note": "autonomous cadastre parcel/linework corner match #11; seed_nearest=0.20m; fit_residual=1.29m"
    },
    {
      "fx": 0.9428530699496643,
      "fy": 0.22569083827893174,
      "lon": -73.55442133764016,
      "lat": 45.36771942573483,
      "source": "cadastre-parcel-corner-match",
      "independent": true,
      "note": "autonomous cadastre parcel/linework corner match #12; seed_nearest=0.22m; fit_residual=0.04m"
    },
    {
      "fx": 0.9739343015855706,
      "fy": 0.41941881491988137,
      "lon": -73.55066446544268,
      "lat": 45.335906144142314,
      "source": "cadastre-parcel-corner-match",
      "independent": true,
      "note": "autonomous cadastre parcel/linework corner match #13; seed_nearest=0.22m; fit_residual=1.86m"
    },
    {
      "fx": 0.4170970532634229,
      "fy": 0.21500834569732938,
      "lon": -73.61796127884539,
      "lat": 45.36947408021593,
      "source": "cadastre-parcel-corner-match",
      "independent": true,
      "note": "autonomous cadastre parcel/linework corner match #14; seed_nearest=0.28m; fit_residual=0.96m"
    },
    {
      "fx": 0.6397565803355706,
      "fy": 0.20154859051038582,
      "lon": -73.59104907166001,
      "lat": 45.37168431083407,
      "source": "cadastre-parcel-corner-match",
      "independent": true,
      "note": "autonomous cadastre parcel/linework corner match #15; seed_nearest=0.33m; fit_residual=0.94m"
    },
    {
      "fx": 0.8093867973993288,
      "fy": 0.27794649481305644,
      "lon": -73.57055033883489,
      "lat": 45.359134463098776,
      "source": "cadastre-parcel-corner-match",
      "independent": true,
      "note": "autonomous cadastre parcel/linework corner match #16; seed_nearest=0.33m; fit_residual=0.52m"
    },
    {
      "fx": 0.6386489356124161,
      "fy": 0.41674819177448075,
      "lon": -73.59118046015179,
      "lat": 45.33634615194923,
      "source": "cadastre-parcel-corner-match",
      "independent": true,
      "note": "autonomous cadastre parcel/linework corner match #17; seed_nearest=0.34m; fit_residual=0.91m"
    },
    {
      "fx": 1.016418047407718,
      "fy": 0.3211389558575668,
      "lon": -73.54552399456985,
      "lat": 45.352045719314205,
      "source": "cadastre-parcel-corner-match",
      "independent": true,
      "note": "autonomous cadastre parcel/linework corner match #18; seed_nearest=0.44m; fit_residual=0.53m"
    },
    {
      "fx": 0.7590391427825777,
      "fy": 0.12190513723763303,
      "lon": -73.57663765108516,
      "lat": 45.38475497581077,
      "source": "cadastre-parcel-corner-match",
      "independent": true,
      "note": "autonomous cadastre parcel/linework corner match #19; seed_nearest=0.48m; fit_residual=1.11m"
    },
    {
      "fx": 0.34806260485738266,
      "fy": 0.3255192878338279,
      "lon": -73.62630751267542,
      "lat": 45.3513302461284,
      "source": "cadastre-parcel-corner-match",
      "independent": true,
      "note": "autonomous cadastre parcel/linework corner match #20; seed_nearest=0.56m; fit_residual=0.61m"
    },
    {
      "fx": 0.9078688653439598,
      "fy": 0.1499698627537092,
      "lon": -73.55864082424267,
      "lat": 45.38014936958238,
      "source": "cadastre-parcel-corner-match",
      "independent": true,
      "note": "autonomous cadastre parcel/linework corner match #21; seed_nearest=0.60m; fit_residual=1.40m"
    },
    {
      "fx": 0.8598993288590604,
      "fy": 0.28033197329970333,
      "lon": -73.56445512320674,
      "lat": 45.35874564092089,
      "source": "cadastre-parcel-corner-match",
      "independent": true,
      "note": "autonomous cadastre parcel/linework corner match #22; seed_nearest=0.75m; fit_residual=1.05m"
    },
    {
      "fx": 0.286049247600671,
      "fy": 0.33201734049851633,
      "lon": -73.63380741762514,
      "lat": 45.35025615449623,
      "source": "cadastre-parcel-corner-match",
      "independent": true,
      "note": "autonomous cadastre parcel/linework corner match #23; seed_nearest=0.81m; fit_residual=0.72m"
    },
    {
      "fx": 0.6196223521476512,
      "fy": 0.5799587351632047,
      "lon": -73.59347439356974,
      "lat": 45.30954506649124,
      "source": "cadastre-parcel-corner-match",
      "independent": true,
      "note": "autonomous cadastre parcel/linework corner match #24; seed_nearest=0.83m; fit_residual=2.02m"
    },
    {
      "fx": 1.2233722866107384,
      "fy": 0.3259284588308605,
      "lon": -73.52052164700102,
      "lat": 45.35125100745211,
      "source": "cadastre-parcel-corner-match",
      "independent": true,
      "note": "autonomous cadastre parcel/linework corner match #25; seed_nearest=0.92m; fit_residual=2.01m"
    },
    {
      "fx": 0.7783055657634229,
      "fy": 0.5059822422077151,
      "lon": -73.57430153278146,
      "lat": 45.3217039522695,
      "source": "cadastre-parcel-corner-match",
      "independent": true,
      "note": "autonomous cadastre parcel/linework corner match #26; seed_nearest=1.10m; fit_residual=1.86m"
    },
    {
      "fx": 0.4752090761241612,
      "fy": 0.53379196031454,
      "lon": -73.61092264082777,
      "lat": 45.31712928622726,
      "source": "cadastre-parcel-corner-match",
      "independent": true,
      "note": "autonomous cadastre parcel/linework corner match #27; seed_nearest=1.14m; fit_residual=0.90m"
    },
    {
      "fx": 0.6067615483557047,
      "fy": 0.08302693805934715,
      "lon": -73.59502490012316,
      "lat": 45.3911472340207,
      "source": "cadastre-parcel-corner-match",
      "independent": true,
      "note": "autonomous cadastre parcel/linework corner match #28; seed_nearest=1.18m; fit_residual=2.99m"
    },
    {
      "fx": 0.41568791946308725,
      "fy": 0.16437430453412466,
      "lon": -73.61814841947864,
      "lat": 45.37779084108712,
      "source": "cadastre-parcel-corner-match",
      "independent": true,
      "note": "autonomous cadastre parcel/linework corner match #29; seed_nearest=1.51m; fit_residual=0.86m"
    },
    {
      "fx": 0.2936995333557046,
      "fy": 0.3874779766350148,
      "lon": -73.63285885507558,
      "lat": 45.34114318354621,
      "source": "cadastre-parcel-corner-match",
      "independent": true,
      "note": "autonomous cadastre parcel/linework corner match #30; seed_nearest=1.56m; fit_residual=1.26m"
    },
    {
      "fx": 0.3689259778859059,
      "fy": 0.20243879822551936,
      "lon": -73.62379888459952,
      "lat": 45.371527192276346,
      "source": "cadastre-parcel-corner-match",
      "independent": true,
      "note": "autonomous cadastre parcel/linework corner match #31; seed_nearest=1.61m; fit_residual=0.72m"
    },
    {
      "fx": 0.5166113936744966,
      "fy": 0.252788853851632,
      "lon": -73.60591503976862,
      "lat": 45.36328768697586,
      "source": "cadastre-parcel-corner-match",
      "independent": true,
      "note": "autonomous cadastre parcel/linework corner match #32; seed_nearest=2.61m; fit_residual=2.93m"
    },
    {
      "fx": 1.1059390074328859,
      "fy": 0.3317507418397626,
      "lon": -73.53473487766462,
      "lat": 45.35028421368905,
      "source": "cadastre-parcel-corner-match",
      "independent": true,
      "note": "autonomous cadastre parcel/linework corner match #33; seed_nearest=2.82m; fit_residual=3.90m"
    },
    {
      "fx": 0.8144711488003357,
      "fy": 0.3781481824866469,
      "lon": -73.56991684959146,
      "lat": 45.34271025204985,
      "source": "cadastre-parcel-corner-match",
      "independent": true,
      "note": "autonomous cadastre parcel/linework corner match #34; seed_nearest=3.22m; fit_residual=2.57m"
    },
    {
      "fx": 0.19856497745805365,
      "fy": 0.350302531537092,
      "lon": -73.64442155798439,
      "lat": 45.3472599226048,
      "source": "cadastre-parcel-corner-match",
      "independent": true,
      "note": "autonomous cadastre parcel/linework corner match #35; seed_nearest=3.98m; fit_residual=3.98m"
    },
    {
      "fx": 0.2330953098741611,
      "fy": 0.42290778004154306,
      "lon": -73.64020589461174,
      "lat": 45.33529876594447,
      "source": "cadastre-parcel-corner-match",
      "independent": true,
      "note": "autonomous cadastre parcel/linework corner match #36; seed_nearest=4.11m; fit_residual=4.28m"
    },
    {
      "fx": 1.2234984532214765,
      "fy": 0.3693712907952522,
      "lon": -73.52044925536552,
      "lat": 45.3441257718509,
      "source": "cadastre-parcel-corner-match",
      "independent": true,
      "note": "autonomous cadastre parcel/linework corner match #37; seed_nearest=4.20m; fit_residual=2.68m"
    },
    {
      "fx": 1.0860816904446309,
      "fy": 0.36173265949554895,
      "lon": -73.5371166744022,
      "lat": 45.345420759968995,
      "source": "cadastre-parcel-corner-match",
      "independent": true,
      "note": "autonomous cadastre parcel/linework corner match #38; seed_nearest=4.57m; fit_residual=4.46m"
    },
    {
      "fx": 0.2414010067114094,
      "fy": 0.28800537833827894,
      "lon": -73.63918796505426,
      "lat": 45.35753403183291,
      "source": "cadastre-parcel-corner-match",
      "independent": true,
      "note": "autonomous cadastre parcel/linework corner match #39; seed_nearest=5.39m; fit_residual=5.65m"
    },
    {
      "fx": 0.6683718278020134,
      "fy": 0.45023762055192884,
      "lon": -73.58767631728138,
      "lat": 45.330865534347154,
      "source": "cadastre-parcel-corner-match",
      "independent": true,
      "note": "autonomous cadastre parcel/linework corner match #40; seed_nearest=6.84m; fit_residual=8.25m"
    },
    {
      "fx": 0.3739841128355705,
      "fy": 0.41972134643916914,
      "lon": -73.62308526563277,
      "lat": 45.335844223429135,
      "source": "cadastre-parcel-corner-match",
      "independent": true,
      "note": "autonomous cadastre parcel/linework corner match #41; seed_nearest=6.87m; fit_residual=6.07m"
    },
    {
      "fx": 0.619370018875839,
      "fy": 0.29085450668249263,
      "lon": -73.59346579669246,
      "lat": 45.356965085487126,
      "source": "cadastre-parcel-corner-match",
      "independent": true,
      "note": "autonomous cadastre parcel/linework corner match #42; seed_nearest=7.02m; fit_residual=7.04m"
    },
    {
      "fx": 0.5483971922231543,
      "fy": 0.4238165337566766,
      "lon": -73.60213788990022,
      "lat": 45.3352558975002,
      "source": "cadastre-parcel-corner-match",
      "independent": true,
      "note": "autonomous cadastre parcel/linework corner match #43; seed_nearest=8.56m; fit_residual=8.91m"
    },
    {
      "fx": 0.47641830955536923,
      "fy": 0.3654534495548961,
      "lon": -73.61089057187044,
      "lat": 45.344818670539986,
      "source": "cadastre-parcel-corner-match",
      "independent": true,
      "note": "autonomous cadastre parcel/linework corner match #44; seed_nearest=9.55m; fit_residual=9.92m"
    },
    {
      "fx": 0.5481202810486576,
      "fy": 0.36217776335311574,
      "lon": -73.60221290012477,
      "lat": 45.34523209425197,
      "source": "cadastre-parcel-corner-match",
      "independent": true,
      "note": "autonomous cadastre parcel/linework corner match #45; seed_nearest=10.77m; fit_residual=11.24m"
    },
    {
      "fx": 0.4982893770973154,
      "fy": 0.4649260478516321,
      "lon": -73.60803095674166,
      "lat": 45.32837786602248,
      "source": "cadastre-parcel-corner-match",
      "independent": true,
      "note": "autonomous cadastre parcel/linework corner match #46; seed_nearest=11.20m; fit_residual=10.23m"
    },
    {
      "fx": 0.6211822304865772,
      "fy": 0.6211215689970325,
      "lon": -73.59314932381113,
      "lat": 45.30277452933308,
      "source": "cadastre-parcel-corner-match",
      "independent": true,
      "note": "autonomous cadastre parcel/linework corner match #47; seed_nearest=11.56m; fit_residual=8.75m"
    },
    {
      "fx": 0.7846728843288591,
      "fy": 0.6169730619406528,
      "lon": -73.57341241085597,
      "lat": 45.30353177924352,
      "source": "cadastre-parcel-corner-match",
      "independent": true,
      "note": "autonomous cadastre parcel/linework corner match #48; seed_nearest=11.91m; fit_residual=9.02m"
    }
  ],
  "neatline": {
    "fx0": 0.0403,
    "fy0": 0.0107,
    "fx1": 1.2279,
    "fy1": 0.6907
  }
}